freediscovery/__init__.py
freediscovery/__main__.py
freediscovery/_version.py
freediscovery/base.py
freediscovery/categorization.py
freediscovery/datasets.py
freediscovery/exceptions.py
freediscovery/feature_weighting.py
freediscovery/interpretation.py
freediscovery/io.py
freediscovery/lsi.py
freediscovery/metrics.py
freediscovery/neighbors.py
freediscovery/preprocessing.py
freediscovery/search.py
freediscovery/sklearn_compat.py
freediscovery/stop_words.py
freediscovery/utils.py
freediscovery/viz.py
freediscovery/cluster/__init__.py
freediscovery/cluster/base.py
freediscovery/cluster/birch.py
freediscovery/cluster/dendrogram.py
freediscovery/cluster/hierarchy.py
freediscovery/cluster/optimal_sampling.py
freediscovery/cluster/utils.py
freediscovery/data/20_newsgroups_3categories.pkl.xz
freediscovery/data/20_newsgroups_micro.pkl
freediscovery/data/ds_001/ground_truth_file.txt
freediscovery/data/ds_001/features/0.7.47.101442_features.txt
freediscovery/data/ds_001/raw/0.7.47.101442.txt
freediscovery/data/ds_001/raw/0.7.47.117435.txt
freediscovery/data/ds_001/raw/0.7.6.28635.txt
freediscovery/data/ds_001/raw/0.7.6.28636.txt
freediscovery/data/ds_001/raw/0.7.6.28637.txt
freediscovery/data/ds_001/raw/0.7.6.28638.txt
freediscovery/data/ds_002/raw/0.7.47.1295128.1.txt
freediscovery/data/ds_002/raw/0.7.47.1295194.2.txt
freediscovery/data/ds_002/raw/0.7.47.341516.1.txt
freediscovery/data/ds_002/raw/0.7.47.812312.txt
freediscovery/data/ds_002/raw/0.7.6.555759.1.txt
freediscovery/data/ds_002/raw/0.7.6.555956.1.txt
freediscovery/engine/__init__.py
freediscovery/engine/base.py
freediscovery/engine/categorization.py
freediscovery/engine/cli.py
freediscovery/engine/cluster.py
freediscovery/engine/email_threading.py
freediscovery/engine/ingestion.py
freediscovery/engine/lsi.py
freediscovery/engine/near_duplicates.py
freediscovery/engine/pipeline.py
freediscovery/engine/search.py
freediscovery/engine/stop_words.py
freediscovery/engine/utils.py
freediscovery/engine/vectorizer.py
freediscovery_stabilizer-1.4.dev0.dist-info/LICENSE
freediscovery_stabilizer-1.4.dev0.dist-info/METADATA
freediscovery_stabilizer-1.4.dev0.dist-info/WHEEL
freediscovery_stabilizer-1.4.dev0.dist-info/entry_points.txt
freediscovery_stabilizer-1.4.dev0.dist-info/top_level.txt
freediscovery_stabilizer-1.4.dev0.dist-info/RECORD
